setup.cfg
setup.py
fcm.egg-info/PKG-INFO
fcm.egg-info/SOURCES.txt
fcm.egg-info/dependency_links.txt
fcm.egg-info/top_level.txt
src/__init__.py
src/core/__init__.py
src/core/annotation.py
src/core/compensate.py
src/core/fcmcollection.py
src/core/fcmdata.py
src/core/fcmexceptions.py
src/core/gate.py
src/core/logicle.py
src/core/subsample.py
src/core/transforms.py
src/core/tree.py
src/core/logicle_ext/Logicle.cpp
src/core/logicle_ext/my_logicle.cpp
src/core/logicle_ext/my_logicle_wrapper.cpp
src/graphics/__init__.py
src/graphics/dimechart.py
src/graphics/experimental.py
src/graphics/plot.py
src/graphics/plot_gate.py
src/graphics/util.py
src/gui/__init__.py
src/gui/mpl_gate.py
src/gui/mpl_qgate.py
src/io/__init__.py
src/io/export_to_fcs.py
src/io/flowjoxml.py
src/io/readfcs.py
src/statistics/__init__.py
src/statistics/cluster.py
src/statistics/component.py
src/statistics/dime.py
src/statistics/distributions.py
src/statistics/dp_cluster.py
src/statistics/kmeans.py
src/statistics/mvnpdf.py
src/statistics/partition.py
src/statistics/util.py