Metadata-Version: 1.1
Name: fcm
Version: 0.9
Summary: Python Flow Cytometry (FCM) Tools
Home-page: http://code.google.com/p/py-fcm/
Author: Jacob Frelinger
Author-email: jacob.frelinger@duke.edu
License: UNKNOWN
Platform: UNKNOWN
Requires: numpy (>=1.3.0)
Requires: scipy (>=0.6)
Requires: dpmix (>=0.1)
Requires: matplotlib (>=1.0)
